aissemble_machine_learning_training/generated/__init__.py
aissemble_machine_learning_training/generated/bootstrap_base.py
aissemble_machine_learning_training/generated/example_machine_learning_pipeline_base.py
aissemble_machine_learning_training/generated/pipeline/pipeline_base.py
aissemble_machine_learning_training/generated/post_action/__init__.py
aissemble_machine_learning_training/generated/post_action/custom_model_conversion_base.py
aissemble_machine_learning_training/generated/post_action/example_custom_conversion_base.py
aissemble_machine_learning_training/generated/post_action/example_freeform_post_action_base.py
aissemble_machine_learning_training/generated/post_action/example_onnx_keras_conversion_base.py
aissemble_machine_learning_training/generated/post_action/example_onnx_sklearn_conversion_base.py
aissemble_machine_learning_training/generated/post_action/onnx_keras_model_conversion_base.py
aissemble_machine_learning_training/generated/post_action/onnx_sklearn_model_conversion_base.py
aissemble_machine_learning_training-2.0.0.dist-info/LICENSE
aissemble_machine_learning_training-2.0.0.dist-info/METADATA
aissemble_machine_learning_training-2.0.0.dist-info/WHEEL
aissemble_machine_learning_training-2.0.0.dist-info/RECORD
