Metadata-Version: 2.3
Name: aissemble-machine-learning-training
Version: 2.0.0
Summary: Machine Learning Training Test Module
License: Apache-2.0
Author: aiSSEMBLE Baseline Community
Author-email: aissemble@bah.com
Requires-Python: >=3.9
Classifier: License :: OSI Approved :: Apache Software License
Classifier: Programming Language :: Python :: 3
Classifier: Programming Language :: Python :: 3.9
Classifier: Programming Language :: Python :: 3.10
Classifier: Programming Language :: Python :: 3.11
Classifier: Programming Language :: Python :: 3.12
Classifier: Programming Language :: Python :: 3.13
Requires-Dist: aissemble-foundation-core-python (==2.0.0)
Requires-Dist: aissemble-foundation-model-lineage (==2.0.0)
Requires-Dist: aissemble-foundation-pdp-client-python (==2.0.0)
Requires-Dist: kafka-python (>=2.0.2,<3.0.0)
Requires-Dist: krausening (>=21)
Requires-Dist: mlflow (>=2.22.0)
Requires-Dist: onnxmltools (>=1.11.1,<2.0.0)
Requires-Dist: pandas (>=1.5.0)
Requires-Dist: protobuf (==4.25.8)
Requires-Dist: pyopenssl (>22.1.0)
Requires-Dist: tf2onnx (>=1.12.1,<2.0.0)
Project-URL: Documentation, https://boozallen.github.io/aissemble
Project-URL: Homepage, https://github.com/boozallen/aissemble
Project-URL: Repository, https://github.com/boozallen/aissemble
